duckduckgo_ai_chat/__init__.py
duckduckgo_ai_chat/__main__.py
duckduckgo_ai_chat/app.py
duckduckgo_ai_chat/cli.py
duckduckgo_ai_chat-0.0.8.dist-info/licenses/LICENSE
duckduckgo_ai_chat-0.0.8.dist-info/METADATA
duckduckgo_ai_chat-0.0.8.dist-info/WHEEL
duckduckgo_ai_chat-0.0.8.dist-info/entry_points.txt
duckduckgo_ai_chat-0.0.8.dist-info/top_level.txt
duckduckgo_ai_chat-0.0.8.dist-info/RECORD
