Metadata-Version: 2.4
Name: duckduckgo-ai-chat
Version: 0.0.8
Summary: CLI to use DuckDuckGo AI Chat service from terminal
Author: Sukhbinder Singh
License: Apache-2.0
Project-URL: Homepage, https://github.com/sukhbinder/duckduckgo-ai-chat
Project-URL: Changelog, https://github.com/sukhbinder/duckduckgo-ai-chat/releases
Project-URL: Issues, https://github.com/sukhbinder/duckduckgo-ai-chat/issues
Project-URL: CI, https://github.com/sukhbinder/duckduckgo-ai-chat/actions
Classifier: License :: OSI Approved :: Apache Software License
Requires-Python: >=3.8
License-File: LICENSE
Requires-Dist: requests
Requires-Dist: colorama
Provides-Extra: test
Requires-Dist: pytest; extra == "test"
Dynamic: license-file
